lullu_util/__init__.py
lullu_util/iteration.py
lullu_util/tmux.py
lullu_util-0.1.2.dist-info/METADATA
lullu_util-0.1.2.dist-info/WHEEL
lullu_util-0.1.2.dist-info/RECORD
